{
  "persons": [
    {
      "name": "Arto Hellas",
      "number": "040-123456",
      "id": 1
    },
    {
      "name": "Ada Lovelace",
      "number": "39-44-5323523",
      "id": 2
    },
    {
      "name": "Mary Poppendieck",
      "number": "39-23-6423122",
      "id": 3
    },
    {
      "name": "Yu Qian",
      "number": "189-3321-3232",
      "id": 5
    },
    {
      "name": "Lele",
      "number": "198-322-5636",
      "id": 6
    },
    {
      "name": "Song Wang",
      "number": "155-2358-33145",
      "id": 8
    }
  ]
}